[
  {
    "日期":"2026-04-02",
    "代码":"159941",
    "名称":"广发纳指100ETF",
    "基金公司":"广发基金",
    "市场":"国内",
    "最新价":1.283,
    "开盘价":1.293,
    "最高价":1.295,
    "最低价":1.278,
    "前收盘价":1.303,
    "成交量":5684552,
    "成交额":730540000.0,
    "涨跌幅(%)":-1.53,
    "涨跌额":-0.02,
    "换手率(%)":null,
    "50日均线":1.1397,
    "距50日线(%)":8.16,
    "120日均线":1.1235,
    "距120日线(%)":9.72,
    "200日均线":1.1858,
    "距200日线(%)":3.95,
    "250日均线":1.2173,
    "距250日线(%)":1.26,
    "52周最高":1.389,
    "52周最低":0.9307,
    "距52周高(%)":-11.25,
    "距52周低(%)":32.45,
    "近1周涨幅":-0.78,
    "近1月涨幅":-4.95,
    "近3月涨幅":-7.52,
    "近6月涨幅":-6.45,
    "近1年涨幅":17.92,
    "今年涨幅":-7.98,
    "溢价率(%)":3.12
  },
  {
    "日期":"2026-04-02",
    "代码":"513100",
    "名称":"国泰纳指100ETF",
    "基金公司":"国泰基金",
    "市场":"国内",
    "最新价":1.721,
    "开盘价":1.745,
    "最高价":1.745,
    "最低价":1.713,
    "前收盘价":1.752,
    "成交量":2113111,
    "成交额":365060000.0,
    "涨跌幅(%)":-1.77,
    "涨跌额":-0.031,
    "换手率(%)":null,
    "50日均线":1.5124,
    "距50日线(%)":8.5,
    "120日均线":1.492,
    "距120日线(%)":9.98,
    "200日均线":1.5764,
    "距200日线(%)":4.1,
    "250日均线":1.6188,
    "距250日线(%)":1.37,
    "52周最高":1.85,
    "52周最低":1.235,
    "距52周高(%)":-11.3,
    "距52周低(%)":32.87,
    "近1周涨幅":-0.77,
    "近1月涨幅":-4.95,
    "近3月涨幅":-7.47,
    "近6月涨幅":-6.44,
    "近1年涨幅":18.23,
    "今年涨幅":-7.94,
    "溢价率(%)":3.91
  },
  {
    "日期":"2026-04-02",
    "代码":"513300",
    "名称":"华夏纳指100ETF",
    "基金公司":"华夏基金",
    "市场":"国内",
    "最新价":2.103,
    "开盘价":2.119,
    "最高价":2.121,
    "最低价":2.098,
    "前收盘价":2.137,
    "成交量":1434044,
    "成交额":302320000.0,
    "涨跌幅(%)":-1.59,
    "涨跌额":-0.034,
    "换手率(%)":null,
    "50日均线":1.9139,
    "距50日线(%)":6.8,
    "120日均线":1.8786,
    "距120日线(%)":8.8,
    "200日均线":1.9808,
    "距200日线(%)":3.19,
    "250日均线":2.031,
    "距250日线(%)":0.64,
    "52周最高":2.3143,
    "52周最低":1.568,
    "距52周高(%)":-11.68,
    "距52周低(%)":30.36,
    "近1周涨幅":-0.79,
    "近1月涨幅":-4.17,
    "近3月涨幅":-7.22,
    "近6月涨幅":-6.88,
    "近1年涨幅":16.91,
    "今年涨幅":-7.61,
    "溢价率(%)":2.11
  },
  {
    "日期":"2026-04-02",
    "代码":"159501",
    "名称":"华安纳指100ETF",
    "基金公司":"华安基金",
    "市场":"国内",
    "最新价":1.596,
    "开盘价":1.623,
    "最高价":1.625,
    "最低价":1.592,
    "前收盘价":1.627,
    "成交量":488023,
    "成交额":78310000.0,
    "涨跌幅(%)":-1.91,
    "涨跌额":-0.031,
    "换手率(%)":null,
    "50日均线":1.4172,
    "距50日线(%)":8.66,
    "120日均线":1.3982,
    "距120日线(%)":10.14,
    "200日均线":1.4776,
    "距200日线(%)":4.22,
    "250日均线":1.5175,
    "距250日线(%)":1.48,
    "52周最高":1.7342,
    "52周最低":1.1569,
    "距52周高(%)":-11.2,
    "距52周低(%)":33.11,
    "近1周涨幅":-0.75,
    "近1月涨幅":-4.92,
    "近3月涨幅":-7.43,
    "近6月涨幅":-6.37,
    "近1年涨幅":18.37,
    "今年涨幅":-7.9,
    "溢价率(%)":2.68
  },
  {
    "日期":"2026-04-02",
    "代码":"159632",
    "名称":"博时纳指100ETF",
    "基金公司":"博时基金",
    "市场":"国内",
    "最新价":1.915,
    "开盘价":1.931,
    "最高价":1.932,
    "最低价":1.908,
    "前收盘价":1.947,
    "成交量":1498943,
    "成交额":287270000.0,
    "涨跌幅(%)":-1.64,
    "涨跌额":-0.032,
    "换手率(%)":null,
    "50日均线":1.7264,
    "距50日线(%)":7.85,
    "120日均线":1.6983,
    "距120日线(%)":9.64,
    "200日均线":1.7921,
    "距200日线(%)":3.9,
    "250日均线":1.8397,
    "距250日线(%)":1.21,
    "52周最高":2.0998,
    "52周最低":1.4075,
    "距52周高(%)":-11.32,
    "距52周低(%)":32.29,
    "近1周涨幅":-0.76,
    "近1月涨幅":-4.95,
    "近3月涨幅":-7.5,
    "近6月涨幅":-6.49,
    "近1年涨幅":17.49,
    "今年涨幅":-7.96,
    "溢价率(%)":1.89
  },
  {
    "日期":"2026-04-02",
    "代码":"159509",
    "名称":"景顺长城纳指100ETF",
    "基金公司":"景顺长城基金",
    "市场":"国内",
    "最新价":1.96,
    "开盘价":1.957,
    "最高价":1.994,
    "最低价":1.946,
    "前收盘价":2.0,
    "成交量":3407113,
    "成交额":669280000.0,
    "涨跌幅(%)":-2.0,
    "涨跌额":-0.04,
    "换手率(%)":null,
    "50日均线":1.463,
    "距50日线(%)":15.96,
    "120日均线":1.4397,
    "距120日线(%)":17.84,
    "200日均线":1.5634,
    "距200日线(%)":8.51,
    "250日均线":1.6302,
    "距250日线(%)":4.06,
    "52周最高":1.9793,
    "52周最低":1.1597,
    "距52周高(%)":-14.29,
    "距52周低(%)":46.29,
    "近1周涨幅":-1.61,
    "近1月涨幅":-5.1,
    "近3月涨幅":-10.16,
    "近6月涨幅":-7.21,
    "近1年涨幅":30.24,
    "今年涨幅":-10.64,
    "溢价率(%)":13.68
  },
  {
    "日期":"2026-04-02",
    "代码":"513800",
    "名称":"南方纳指100ETF",
    "基金公司":"南方基金",
    "市场":"国内",
    "最新价":1.69,
    "开盘价":1.719,
    "最高价":1.72,
    "最低价":1.683,
    "前收盘价":1.738,
    "成交量":1297067,
    "成交额":220650000.0,
    "涨跌幅(%)":-2.76,
    "涨跌额":-0.048,
    "换手率(%)":null,
    "50日均线":1.3779,
    "距50日线(%)":25.42,
    "120日均线":1.4114,
    "距120日线(%)":22.44,
    "200日均线":1.4773,
    "距200日线(%)":16.98,
    "250日均线":1.5116,
    "距250日线(%)":14.32,
    "52周最高":1.883,
    "52周最低":1.2198,
    "距52周高(%)":-8.23,
    "距52周低(%)":41.67,
    "近1周涨幅":1.57,
    "近1月涨幅":-7.59,
    "近3月涨幅":5.11,
    "近6月涨幅":7.14,
    "近1年涨幅":26.0,
    "今年涨幅":3.52,
    "溢价率(%)":-0.15
  },
  {
    "日期":"2026-04-02",
    "代码":"159513",
    "名称":"大成纳指100ETF",
    "基金公司":"大成基金",
    "市场":"国内",
    "最新价":1.415,
    "开盘价":1.43,
    "最高价":1.43,
    "最低价":1.409,
    "前收盘价":1.438,
    "成交量":623144,
    "成交额":88450000.0,
    "涨跌幅(%)":-1.6,
    "涨跌额":-0.023,
    "换手率(%)":null,
    "50日均线":1.2727,
    "距50日线(%)":8.11,
    "120日均线":1.2543,
    "距120日线(%)":9.7,
    "200日均线":1.3237,
    "距200日线(%)":3.95,
    "250日均线":1.3585,
    "距250日线(%)":1.28,
    "52周最高":1.5497,
    "52周最低":1.0404,
    "距52周高(%)":-11.22,
    "距52周低(%)":32.25,
    "近1周涨幅":-0.81,
    "近1月涨幅":-4.99,
    "近3月涨幅":-7.43,
    "近6月涨幅":-6.39,
    "近1年涨幅":17.78,
    "今年涨幅":-7.89,
    "溢价率(%)":1.66
  },
  {
    "日期":"2026-04-02",
    "代码":"159696",
    "名称":"易方达纳指100ETF",
    "基金公司":"易方达基金",
    "市场":"国内",
    "最新价":1.577,
    "开盘价":1.605,
    "最高价":1.605,
    "最低价":1.55,
    "前收盘价":1.606,
    "成交量":265411,
    "成交额":42020000.0,
    "涨跌幅(%)":-1.81,
    "涨跌额":-0.029,
    "换手率(%)":null,
    "50日均线":1.4005,
    "距50日线(%)":8.96,
    "120日均线":1.3825,
    "距120日线(%)":10.38,
    "200日均线":1.4617,
    "距200日线(%)":4.4,
    "250日均线":1.5016,
    "距250日线(%)":1.62,
    "52周最高":1.7176,
    "52周最低":1.1443,
    "距52周高(%)":-11.16,
    "距52周低(%)":33.36,
    "近1周涨幅":-0.77,
    "近1月涨幅":-4.93,
    "近3月涨幅":-7.4,
    "近6月涨幅":-6.29,
    "近1年涨幅":18.69,
    "今年涨幅":-7.88,
    "溢价率(%)":2.39
  },
  {
    "日期":"2026-04-02",
    "代码":"513130",
    "名称":"华泰柏瑞纳指100ETF",
    "基金公司":"华泰柏瑞基金",
    "市场":"国内",
    "最新价":0.591,
    "开盘价":0.599,
    "最高价":0.6,
    "最低价":0.588,
    "前收盘价":0.605,
    "成交量":74754689,
    "成交额":4431150000.0,
    "涨跌幅(%)":-2.31,
    "涨跌额":-0.014,
    "换手率(%)":null,
    "50日均线":0.7002,
    "距50日线(%)":-13.67,
    "120日均线":0.6983,
    "距120日线(%)":-13.43,
    "200日均线":0.7249,
    "距200日线(%)":-16.61,
    "250日均线":0.7286,
    "距250日线(%)":-17.03,
    "52周最高":0.8577,
    "52周最低":0.5905,
    "距52周高(%)":-29.52,
    "距52周低(%)":2.37,
    "近1周涨幅":-3.62,
    "近1月涨幅":-8.06,
    "近3月涨幅":-16.01,
    "近6月涨幅":-29.52,
    "近1年涨幅":-16.47,
    "今年涨幅":-19.27,
    "溢价率(%)":-0.14
  }
]